cleancloud/__init__.py
cleancloud/cli.py
cleancloud/config/schema.py
cleancloud/core/__init__.py
cleancloud/core/confidence.py
cleancloud/core/evidence.py
cleancloud/core/finding.py
cleancloud/core/risk.py
cleancloud/doctor/__init__.py
cleancloud/doctor/aws.py
cleancloud/doctor/azure.py
cleancloud/doctor/command.py
cleancloud/doctor/common.py
cleancloud/doctor/runner.py
cleancloud/filtering/tags.py
cleancloud/output/csv.py
cleancloud/output/feedback.py
cleancloud/output/human.py
cleancloud/output/json.py
cleancloud/output/progress.py
cleancloud/output/summary.py
cleancloud/policy/__init__.py
cleancloud/policy/exit_policy.py
cleancloud/providers/__init__.py
cleancloud/providers/aws/__init__.py
cleancloud/providers/aws/scan.py
cleancloud/providers/aws/session.py
cleancloud/providers/aws/validate.py
cleancloud/providers/aws/rules/__init__.py
cleancloud/providers/aws/rules/cloudwatch_inactive.py
cleancloud/providers/aws/rules/ebs_snapshot_old.py
cleancloud/providers/aws/rules/ebs_unattached.py
cleancloud/providers/aws/rules/untagged_resources.py
cleancloud/providers/azure/__init__.py
cleancloud/providers/azure/scan.py
cleancloud/providers/azure/session.py
cleancloud/providers/azure/validate.py
cleancloud/providers/azure/rules/__init__.py
cleancloud/providers/azure/rules/ebs_snapshots_old.py
cleancloud/providers/azure/rules/public_ip_unused.py
cleancloud/providers/azure/rules/unattached_managed_disks.py
cleancloud/providers/azure/rules/untagged_resources.py
cleancloud/safety/__init__.py
cleancloud/safety/aws/__init__.py
cleancloud/safety/aws/allowlist.py
cleancloud/safety/azure/__init__.py
cleancloud/safety/azure/allowlist.py
cleancloud/scan/__init__.py
cleancloud/scan/command.py
cleancloud-0.6.0.dist-info/licenses/LICENSE
cleancloud-0.6.0.dist-info/METADATA
cleancloud-0.6.0.dist-info/WHEEL
cleancloud-0.6.0.dist-info/entry_points.txt
cleancloud-0.6.0.dist-info/top_level.txt
cleancloud-0.6.0.dist-info/RECORD
