Metadata-Version: 2.4
Name: cleancloud
Version: 0.6.0
Summary: Safe, conservative cloud hygiene scanning for AWS and Azure
Author-email: CleanCloud <suresh.csdp@gmail.com>
License: MIT
Project-URL: Homepage, https://github.com/cleancloud-io/cleancloud
Project-URL: Documentation, https://github.com/cleancloud-io/cleancloud#readme
Project-URL: Repository, https://github.com/cleancloud-io/cleancloud
Project-URL: Issues, https://github.com/cleancloud-io/cleancloud/issues
Keywords: aws,azure,cloud,hygiene,devops,sre,infrastructure
Classifier: Development Status :: 3 - Alpha
Classifier: Intended Audience :: Developers
Classifier: Intended Audience :: System Administrators
Classifier: License :: OSI Approved :: MIT License
Classifier: Programming Language :: Python :: 3
Classifier: Programming Language :: Python :: 3.10
Classifier: Programming Language :: Python :: 3.11
Classifier: Programming Language :: Python :: 3.12
Classifier: Topic :: System :: Systems Administration
Classifier: Topic :: Utilities
Requires-Python: >=3.10
License-File: LICENSE
Requires-Dist: click>=8.0.0
Requires-Dist: PyYAML>=6.0
Provides-Extra: aws
Requires-Dist: boto3>=1.26.0; extra == "aws"
Requires-Dist: botocore>=1.29.0; extra == "aws"
Provides-Extra: azure
Requires-Dist: azure-identity>=1.15.0; extra == "azure"
Requires-Dist: azure-mgmt-resource>=23.0.0; extra == "azure"
Requires-Dist: azure-mgmt-compute>=30.0.0; extra == "azure"
Requires-Dist: azure-mgmt-network>=25.0.0; extra == "azure"
Requires-Dist: azure-core>=1.29.0; extra == "azure"
Provides-Extra: all
Requires-Dist: cleancloud[aws,azure]; extra == "all"
Provides-Extra: dev
Requires-Dist: pytest>=8.0.0; extra == "dev"
Requires-Dist: pytest-mock>=3.12.0; extra == "dev"
Requires-Dist: pytest-cov>=4.1.0; extra == "dev"
Requires-Dist: ruff>=0.1.0; extra == "dev"
Requires-Dist: mypy>=1.7.0; extra == "dev"
Requires-Dist: black>=23.0.0; extra == "dev"
Dynamic: license-file
